litechain/__init__.py
litechain/contrib/__init__.py
litechain/contrib/llms/__init__.py
litechain/contrib/llms/gpt4all_chain.py
litechain/contrib/llms/open_ai.py
litechain/core/__init__.py
litechain/core/chain.py
litechain/utils/__init__.py
litechain/utils/_typing.py
litechain/utils/async_generator.py
litechain/utils/chain.py
tests/__init__.py
litechain-0.1.6.dist-info/LICENSE
litechain-0.1.6.dist-info/METADATA
litechain-0.1.6.dist-info/WHEEL
litechain-0.1.6.dist-info/top_level.txt
litechain-0.1.6.dist-info/RECORD
